covfee/__init__.py
covfee/_version.py
covfee/covfee_folder.py
covfee/utils.py
covfee/cli/__init__.py
covfee/cli/utils.py
covfee/cli/commands/__init__.py
covfee/cli/commands/dev.py
covfee/cli/commands/launch.py
covfee/client/bundles/436.js
covfee/client/bundles/436.js.LICENSE.txt
covfee/client/bundles/admin.js
covfee/client/bundles/admin.js.LICENSE.txt
covfee/client/bundles/main.js
covfee/client/bundles/main.js.LICENSE.txt
covfee/server/__init__.py
covfee/server/config.py
covfee/server/package.json
covfee/server/rtstore.py
covfee/server/start.py
covfee/server/orm/__init__.py
covfee/server/orm/db.py
covfee/server/orm/hit.py
covfee/server/orm/project.py
covfee/server/orm/task.py
covfee/server/orm/user.py
covfee/server/rest_api/__init__.py
covfee/server/rest_api/api.py
covfee/server/rest_api/auth.py
covfee/server/socketio/__init__.py
covfee/server/socketio/reduxStore.js
covfee/server/socketio/redux_store.py
covfee/server/socketio/socketio.py
covfee/server/tasks/__init__.py
covfee/server/tasks/base.py
covfee/server/tasks/continous_keypoint.py
covfee/server/tasks/continuous_1d.py
covfee/server/tasks/video_recall.py
covfee/server/tasks/videocall.py
covfee/server/templates/404.html
covfee/server/templates/admin.html
covfee/server/templates/app.html
covfee/server/templates/externals.html
covfee/server/utils/__init__.py
covfee/server/utils/packer.py
covfee/server/utils/agora/__init__.py
covfee/server/utils/agora/access_token.py
covfee/server/utils/agora/rtc_token_builder.py
covfee/shared/__init__.py
covfee/shared/package.json
covfee/shared/schemata.json
covfee/shared/schemata.py
covfee/shared/validator/__init__.py
covfee/shared/validator/ajv_validator.py
covfee/shared/validator/index.js
covfee/shared/validator/validation_errors.py
covfee/shared/validator/validator.js
covfee/shared/validator/validator_service.js
covfee-0.0.36.dist-info/LICENSE
covfee-0.0.36.dist-info/METADATA
covfee-0.0.36.dist-info/WHEEL
covfee-0.0.36.dist-info/entry_points.txt
covfee-0.0.36.dist-info/top_level.txt
covfee-0.0.36.dist-info/RECORD
