Metadata-Version: 2.1
Name: covfee
Version: 0.0.36
Summary: Continuous video feedback tool
Author: Jose Vargas
Author-email: josedvq@gmail.com
Requires-Python: >=3.6
License-File: LICENSE
Requires-Dist: Flask (==2.1.0)
Requires-Dist: werkzeug (==2.0.3)
Requires-Dist: MarkupSafe (==2.0.1)
Requires-Dist: flask-cors (==3.*)
Requires-Dist: SQLAlchemy (==1.4.*)
Requires-Dist: Flask-SQLAlchemy (==2.*)
Requires-Dist: flask-socketio (==5.*)
Requires-Dist: requests (==2.*)
Requires-Dist: gunicorn (==20.*)
Requires-Dist: flask-jwt-extended (==3.*)
Requires-Dist: click (==8.*)
Requires-Dist: pandas (==1.*)
Requires-Dist: jsonschema (==3.*)
Requires-Dist: halo (==0.*)
Requires-Dist: colorama (==0.4.*)
Requires-Dist: pyzmq (==22.*)
Requires-Dist: numpy (==1.*)
Requires-Dist: zipstream-new (==1.*)
Requires-Dist: construct (==2.*)
Requires-Dist: google-auth (==2.*)
